{
  "recipes": [
    {
      "category": "반려묘",
      "title": "사과와 당근 트릿",
      "number": 1,
      "level": "쉬움",
      "time": 20,
      "ingredients": {
        "apple": "1개",
        "carrot": "1개",
        "honey": "1작은술"
      },
      "description": "사과와 당근을 잘게 다진 후 꿀과 함께 섞어준다. 트레이에 얹어 150도로 예열된 오븐에서 15분 동안 구워준다."
    },
    {
      "category": "",
      "title": "",
      "number": 0,
      "level": "",
      "time": 0,
      "ingredients": {
        "apple": "",
        "carrot": "",
        "honey": ""
      },
      "description": ""
    }
  ]
}
